greg/aux_functions.py
greg/classes.py
greg/commands.py
greg/parser.py
greg/data/greg.conf
Greg-0.4.8.dist-info/COPYING
Greg-0.4.8.dist-info/METADATA
Greg-0.4.8.dist-info/WHEEL
Greg-0.4.8.dist-info/entry_points.txt
Greg-0.4.8.dist-info/top_level.txt
Greg-0.4.8.dist-info/RECORD
