Metadata-Version: 2.1
Name: Greg
Version: 0.4.8
Summary: A command-line podcast aggregator
Home-page: https://github.com/manolomartinez/greg
Author: Manolo Martínez
Author-email: manolo@austrohungaro.com
License: GPLv3
Platform: UNKNOWN
Requires-Dist: feedparser
